pyconfigvar/__init__.py
pyconfigvar-1.0.0.dist-info/DESCRIPTION.rst
pyconfigvar-1.0.0.dist-info/METADATA
pyconfigvar-1.0.0.dist-info/RECORD
pyconfigvar-1.0.0.dist-info/WHEEL
pyconfigvar-1.0.0.dist-info/metadata.json
pyconfigvar-1.0.0.dist-info/top_level.txt
