Metadata-Version: 2.0
Name: pyconfigvar
Version: 1.0.0
Summary: Manage required and optional environment variables in your scripts.
Home-page: https://github.com/kfb/pyconfigvar
Author: kfb
Author-email: kaleidoscopicfilmstripblues@gmail.com
License: BSD
Keywords: environment
Platform: UNKNOWN
Classifier: Development Status :: 4 - Beta
Classifier: Intended Audience :: Developers
Classifier: Topic :: Software Development :: Libraries :: Python Modules
Classifier: License :: OSI Approved :: BSD License
Classifier: Programming Language :: Python :: 3
